tk_translate/__init__.py
tk_translate/httprequests.py
tk_translate/translationbackends.py
tk_translate-0.5.dist-info/WHEEL
tk_translate-0.5.dist-info/METADATA
tk_translate-0.5.dist-info/RECORD
