Metadata-Version: 2.1
Name: tk_translate
Version: 0.5
Summary: Utilizes translationbackends in trivial from→to texteditor
Home-page: https://fossil.include-once.org/pagetranslate/
License: MITL
Keywords: translation
Requires-Python: >= 3.8
Classifier: License :: OSI Approved :: MIT License
Classifier: Development Status :: 4 - Beta
Requires-Dist: PySimpleGUI (>=4.37)
Requires-Dist: requests
